README
data.py
mydesire.py
setup.py
mydesire.egg-info/PKG-INFO
mydesire.egg-info/SOURCES.txt
mydesire.egg-info/dependency_links.txt
mydesire.egg-info/top_level.txt