Metadata-Version: 1.1
Name: mydesire
Version: 0.0.1
Summary: Korean version of loremipsum
Home-page: https://github.com/dokenzy/mydesire
Author: dokenzy
Author-email: dokenzy@gmail.com
License: MIT License
Keywords: korean,loremipsum,My desire,Kim koo,Kim Gu
Platform: UNKNOWN
Classifier: Development Status :: 3 - Alpha
Classifier: Intended Audience :: Developers
Classifier: License :: OSI Approved :: MIT License
Classifier: Programming Language :: Python
Classifier: Programming Language :: Python :: 3
Classifier: Operating System :: OS Independent
Classifier: Topic :: Utilities
Classifier: Topic :: Text Processing :: General
